blockkit/__init__.py
blockkit/attributes.py
blockkit/blocks.py
blockkit/elements.py
blockkit/exceptions.py
blockkit/fixed_blocks.py
blockkit/fixed_elements.py
blockkit/generics.py
blockkit/messages.py
blockkit/objects.py
blockkit/quick_blocks.py
blockkit/validators.py
blockkit/views.py
tests/__init__.py
tests/conftest.py
tests/fixtures.py
tests/test_attributes.py
tests/test_blocks.py
tests/test_elements.py
tests/test_exceptions.py
tests/test_fixed_blocks.py
tests/test_fixed_elements.py
tests/test_generics.py
tests/test_messages.py
tests/test_objects.py
tests/test_quick_blocks.py
tests/test_validators.py
tests/test_views.py
tests/snapshots/__init__.py
tests/snapshots/snap_test_blocks.py
tests/snapshots/snap_test_composition.py
tests/snapshots/snap_test_elements.py
tests/snapshots/snap_test_fixed_blocks.py
tests/snapshots/snap_test_fixed_elements.py
tests/snapshots/snap_test_helper_blocks.py
tests/snapshots/snap_test_messages.py
tests/snapshots/snap_test_objects.py
tests/snapshots/snap_test_quick_blocks.py
tests/snapshots/snap_test_views.py
slacktools_blockkit-0.11.0.dist-info/LICENSE
slacktools_blockkit-0.11.0.dist-info/METADATA
slacktools_blockkit-0.11.0.dist-info/WHEEL
slacktools_blockkit-0.11.0.dist-info/top_level.txt
slacktools_blockkit-0.11.0.dist-info/RECORD
